pyfamilysafety/__init__.py
pyfamilysafety/_version.py
pyfamilysafety/account.py
pyfamilysafety/api.py
pyfamilysafety/application.py
pyfamilysafety/const.py
pyfamilysafety/device.py
pyfamilysafety/enum.py
pyfamilysafety/exceptions.py
pyfamilysafety/helpers.py
pyfamilysafety/authenticator/__init__.py
pyfamilysafety/authenticator/const.py
pyfamilysafety-1.1.2.dist-info/LICENSE
pyfamilysafety-1.1.2.dist-info/METADATA
pyfamilysafety-1.1.2.dist-info/WHEEL
pyfamilysafety-1.1.2.dist-info/entry_points.txt
pyfamilysafety-1.1.2.dist-info/top_level.txt
pyfamilysafety-1.1.2.dist-info/RECORD
